{"chunk_definitions":[{"row":251,"row_count":1,"visible":true,"expansion_state":0,"options":{"engine":"r","label":"setup-problem3","message":false,"warning":false,"dev":"png"},"document_id":"A29F0582","chunk_id":"cgzj6lskfd19x","chunk_label":"setup-problem3"},{"row":258,"row_count":1,"visible":true,"expansion_state":0,"options":{},"document_id":"A29F0582","chunk_id":"cdr1vqkdxv9ur","chunk_label":"unnamed-chunk-1"},{"row":275,"row_count":1,"visible":true,"expansion_state":0,"options":{},"document_id":"A29F0582","chunk_id":"cap77dzv7z30b","chunk_label":"unnamed-chunk-2"},{"row":286,"row_count":1,"visible":true,"expansion_state":0,"options":{},"document_id":"A29F0582","chunk_id":"ceqn592qzqxf6","chunk_label":"unnamed-chunk-3"},{"row":343,"row_count":1,"visible":true,"expansion_state":0,"options":{},"document_id":"A29F0582","chunk_id":"c06qupasm5vqi","chunk_label":"unnamed-chunk-4"},{"row":416,"row_count":1,"visible":true,"expansion_state":0,"options":{},"document_id":"A29F0582","chunk_id":"cmep8cschg1u0","chunk_label":"setup-problem4"},{"row":479,"row_count":1,"visible":true,"expansion_state":0,"options":{"engine":"r","label":"unnamed-chunk-4","dev":"png"},"document_id":"A29F0582","chunk_id":"cw98i0bd9ey08","chunk_label":"unnamed-chunk-5"},{"row":487,"row_count":1,"visible":true,"expansion_state":0,"options":{"engine":"r","label":"unnamed-chunk-10","dev":"png"},"document_id":"A29F0582","chunk_id":"cc2jl06tux0fb","chunk_label":"unnamed-chunk-6"}],"doc_write_time":1771810977}